{
   "min_position": 6,
   "has_more_items": true,
   "items_html": "Bike",
   "new_latent_count": 2,
   "data": {
      "length": 24,
      "text": "Excepteur sint occaecat cupidatat non proident, sunt in culpa qui officia deserunt mollit anim id est laborum."
   },
   "numericalArray": [
      30,
      26,
      29,
      26,
      20
   ],
   "StringArray": [
      "Carbon",
      "Carbon",
      "Oxygen",
      "Carbon"
   ],
   "multipleTypesArray": 3,
   "objArray": [
      {
         "class": "lower",
         "age": 3
      },
      {
         "class": "lower",
         "age": 2
      },
      {
         "class": "upper",
         "age": 0
      },
      {
         "class": "upper",
         "age": 8
      },
      {
         "class": "middle",
         "age": 5
      }
   ]
}
